{"name":"Instance Adapter for Microsoft Dynamics CRM","tagline":"Using Connector for Microsoft Dynamics to integrate two Dynamics CRM instances","body":"This is an additional adapter for use with Connector for Microsoft Dynamics that allows for the synchronization of data between two Microsoft Dynamics CRM organizations.  The adapter allows for communication between two endpoints that exist on any authentication/hosting environment (on-premises, online, IFD, etc.)  This means that you can leverage this adapter to move Microsoft Dynamics CRM data between test and production servers or from on-premises to the cloud.\r\n\r\nMore information on Connector for Microsoft Dynamics can be found here: http://blogs.msdn.com/b/dynamicsconnector\r\n","google":"","note":"Don't delete this file! It's used internally to help with page regeneration."}